abeinterpreter.py
abeinterpreter-1.2.dist-info/METADATA
abeinterpreter-1.2.dist-info/WHEEL
abeinterpreter-1.2.dist-info/licenses/LICENSE
abeinterpreter-1.2.dist-info/RECORD
