Metadata-Version: 2.1
Name: AbeInterpreter
Version: 1.2
Summary: Unleash the power of the tale of Abraham.
Project-URL: Homepage, https://www.github.com/TheByronHimes/Abraham
Project-URL: Online Interpreter, https://www.byronhimes.com/abraham
Author-email: Byron Himes <byro93@live.com>
Classifier: License :: OSI Approved :: GNU General Public License v3 (GPLv3)
Classifier: Operating System :: OS Independent
Classifier: Programming Language :: Python :: 3
Requires-Python: >=3.7
